{
  "date" : "Tue, 06 May, 2025 15:45:43 +0000",
  "doco" : "For each file: start is seconds after start activity occurred. Length = milliseconds activity took",
  "files" : [
    {
      "name" : "/fsh-generated/resources/ImplementationGuide-ans.document.fr.core.json",
      "size" : 36916,
      "processes" : [
        {
          "activity" : "load",
          "start" : 54,
          "length" : 16
        },
        {
          "activity" : "scan",
          "start" : 57,
          "length" : 1
        },
        {
          "activity" : "checkR4R4B",
          "start" : 57,
          "length" : 5
        },
        {
          "activity" : "generateNarratives",
          "start" : 57,
          "length" : 255
        },
        {
          "activity" : "validate",
          "start" : 87,
          "length" : 22341
        },
        {
          "activity" : "scanForUsageStats",
          "start" : 109,
          "length" : 1
        },
        {
          "activity" : "generate1",
          "start" : 109,
          "length" : 145
        },
        {
          "activity" : "generate2",
          "start" : 120,
          "length" : 240
        },
        {
          "activity" : "generateValidationPack",
          "start" : 174,
          "length" : 6
        },
        {
          "activity" : "scanExamplesForR5",
          "start" : 207,
          "length" : 1
        }
      ]
    },
    {
      "name" : "fsh-generated/resources/StructureDefinition-Auteur.json",
      "size" : 2783,
      "processes" : [
        {
          "activity" : "loadResources",
          "start" : 52,
          "length" : 9
        },
        {
          "activity" : "load",
          "start" : 53,
          "length" : 12
        },
        {
          "activity" : "generateSnapshots",
          "start" : 54,
          "length" : 12
        },
        {
          "activity" : "scan",
          "start" : 57,
          "length" : 1
        },
        {
          "activity" : "loadDepInfo",
          "start" : 57,
          "length" : 1
        },
        {
          "activity" : "generateNarratives",
          "start" : 58,
          "length" : 39
        },
        {
          "activity" : "validate",
          "start" : 61,
          "length" : 164
        },
        {
          "activity" : "checkConformanceResources",
          "start" : 109,
          "length" : 1
        },
        {
          "activity" : "generateLogicalMaps",
          "start" : 109,
          "length" : 1
        },
        {
          "activity" : "generate1",
          "start" : 109,
          "length" : 44
        },
        {
          "activity" : "generate2",
          "start" : 120,
          "length" : 249
        },
        {
          "activity" : "generate2",
          "start" : 143,
          "length" : 384
        },
        {
          "activity" : "generateValidationPack",
          "start" : 174,
          "length" : 2
        },
        {
          "activity" : "scanProfilesForR5",
          "start" : 207,
          "length" : 1
        }
      ]
    },
    {
      "name" : "fsh-generated/resources/StructureDefinition-Consentement.json",
      "size" : 2209,
      "processes" : [
        {
          "activity" : "loadResources",
          "start" : 52,
          "length" : 9
        },
        {
          "activity" : "load",
          "start" : 53,
          "length" : 12
        },
        {
          "activity" : "generateSnapshots",
          "start" : 54,
          "length" : 27
        },
        {
          "activity" : "load-configure",
          "start" : 57,
          "length" : 1
        },
        {
          "activity" : "generateNarratives",
          "start" : 58,
          "length" : 12
        },
        {
          "activity" : "validate",
          "start" : 61,
          "length" : 85
        },
        {
          "activity" : "generate1",
          "start" : 109,
          "length" : 35
        },
        {
          "activity" : "generate2",
          "start" : 120,
          "length" : 142
        },
        {
          "activity" : "generate2",
          "start" : 144,
          "length" : 96
        },
        {
          "activity" : "generateValidationPack",
          "start" : 174,
          "length" : 1
        }
      ]
    },
    {
      "name" : "fsh-generated/resources/StructureDefinition-DestinatairePrevu.json",
      "size" : 2220,
      "processes" : [
        {
          "activity" : "loadResources",
          "start" : 52,
          "length" : 8
        },
        {
          "activity" : "load",
          "start" : 53,
          "length" : 15
        },
        {
          "activity" : "generateSnapshots",
          "start" : 54,
          "length" : 43
        },
        {
          "activity" : "generateNarratives",
          "start" : 58,
          "length" : 9
        },
        {
          "activity" : "validate",
          "start" : 61,
          "length" : 49
        },
        {
          "activity" : "generate1",
          "start" : 109,
          "length" : 36
        },
        {
          "activity" : "generate2",
          "start" : 120,
          "length" : 107
        },
        {
          "activity" : "generate2",
          "start" : 144,
          "length" : 82
        },
        {
          "activity" : "generateValidationPack",
          "start" : 174,
          "length" : 1
        }
      ]
    },
    {
      "name" : "fsh-generated/resources/StructureDefinition-DocumentDeReference.json",
      "size" : 1859,
      "processes" : [
        {
          "activity" : "loadResources",
          "start" : 52,
          "length" : 9
        },
        {
          "activity" : "load",
          "start" : 53,
          "length" : 16
        },
        {
          "activity" : "generateSnapshots",
          "start" : 54,
          "length" : 44
        },
        {
          "activity" : "generateNarratives",
          "start" : 58,
          "length" : 10
        },
        {
          "activity" : "validate",
          "start" : 61,
          "length" : 50
        },
        {
          "activity" : "generate1",
          "start" : 109,
          "length" : 31
        },
        {
          "activity" : "generate2",
          "start" : 121,
          "length" : 108
        },
        {
          "activity" : "generate2",
          "start" : 144,
          "length" : 79
        }
      ]
    },
    {
      "name" : "fsh-generated/resources/StructureDefinition-EnteteDocument.json",
      "size" : 10981,
      "processes" : [
        {
          "activity" : "loadResources",
          "start" : 52,
          "length" : 8
        },
        {
          "activity" : "load",
          "start" : 53,
          "length" : 13
        },
        {
          "activity" : "generateSnapshots",
          "start" : 54,
          "length" : 49
        },
        {
          "activity" : "generateNarratives",
          "start" : 58,
          "length" : 24
        },
        {
          "activity" : "validate",
          "start" : 61,
          "length" : 190
        },
        {
          "activity" : "scanForUsageStats",
          "start" : 109,
          "length" : 1
        },
        {
          "activity" : "generate1",
          "start" : 109,
          "length" : 119
        },
        {
          "activity" : "generate2",
          "start" : 121,
          "length" : 204
        },
        {
          "activity" : "generate2",
          "start" : 144,
          "length" : 203
        },
        {
          "activity" : "generateValidationPack",
          "start" : 174,
          "length" : 3
        }
      ]
    },
    {
      "name" : "fsh-generated/resources/StructureDefinition-Evenement.json",
      "size" : 6714,
      "processes" : [
        {
          "activity" : "loadResources",
          "start" : 52,
          "length" : 9
        },
        {
          "activity" : "load",
          "start" : 53,
          "length" : 10
        },
        {
          "activity" : "generateSnapshots",
          "start" : 54,
          "length" : 50
        },
        {
          "activity" : "generateNarratives",
          "start" : 58,
          "length" : 22
        },
        {
          "activity" : "validate",
          "start" : 62,
          "length" : 212
        },
        {
          "activity" : "generate1",
          "start" : 110,
          "length" : 83
        },
        {
          "activity" : "generate2",
          "start" : 121,
          "length" : 193
        },
        {
          "activity" : "generate2",
          "start" : 144,
          "length" : 83
        },
        {
          "activity" : "generateValidationPack",
          "start" : 174,
          "length" : 3
        }
      ]
    },
    {
      "name" : "fsh-generated/resources/StructureDefinition-Informateur.json",
      "size" : 1724,
      "processes" : [
        {
          "activity" : "loadResources",
          "start" : 53,
          "length" : 8
        },
        {
          "activity" : "load",
          "start" : 53,
          "length" : 9
        },
        {
          "activity" : "generateSnapshots",
          "start" : 54,
          "length" : 44
        },
        {
          "activity" : "generateNarratives",
          "start" : 58,
          "length" : 10
        },
        {
          "activity" : "validate",
          "start" : 62,
          "length" : 35
        },
        {
          "activity" : "generate1",
          "start" : 110,
          "length" : 43
        },
        {
          "activity" : "generate2",
          "start" : 121,
          "length" : 96
        },
        {
          "activity" : "generate2",
          "start" : 144,
          "length" : 38
        },
        {
          "activity" : "generateValidationPack",
          "start" : 174,
          "length" : 1
        }
      ]
    },
    {
      "name" : "fsh-generated/resources/StructureDefinition-OperateurSaisie.json",
      "size" : 1825,
      "processes" : [
        {
          "activity" : "loadResources",
          "start" : 53,
          "length" : 8
        },
        {
          "activity" : "load",
          "start" : 53,
          "length" : 10
        },
        {
          "activity" : "generateSnapshots",
          "start" : 54,
          "length" : 34
        },
        {
          "activity" : "generateNarratives",
          "start" : 58,
          "length" : 11
        },
        {
          "activity" : "validate",
          "start" : 62,
          "length" : 51
        },
        {
          "activity" : "scanForUsageStats",
          "start" : 109,
          "length" : 1
        },
        {
          "activity" : "generate1",
          "start" : 110,
          "length" : 31
        },
        {
          "activity" : "generate2",
          "start" : 121,
          "length" : 76
        },
        {
          "activity" : "generate2",
          "start" : 144,
          "length" : 68
        },
        {
          "activity" : "generateValidationPack",
          "start" : 174,
          "length" : 1
        }
      ]
    },
    {
      "name" : "fsh-generated/resources/StructureDefinition-Participant.json",
      "size" : 2609,
      "processes" : [
        {
          "activity" : "loadResources",
          "start" : 53,
          "length" : 8
        },
        {
          "activity" : "load",
          "start" : 53,
          "length" : 10
        },
        {
          "activity" : "generateSnapshots",
          "start" : 54,
          "length" : 7
        },
        {
          "activity" : "load-configure",
          "start" : 57,
          "length" : 1
        },
        {
          "activity" : "generateNarratives",
          "start" : 58,
          "length" : 9
        },
        {
          "activity" : "validate",
          "start" : 62,
          "length" : 73
        },
        {
          "activity" : "generate1",
          "start" : 110,
          "length" : 49
        },
        {
          "activity" : "generate2",
          "start" : 121,
          "length" : 83
        },
        {
          "activity" : "generate2",
          "start" : 144,
          "length" : 66
        },
        {
          "activity" : "generateValidationPack",
          "start" : 174,
          "length" : 1
        }
      ]
    },
    {
      "name" : "fsh-generated/resources/StructureDefinition-Patient.json",
      "size" : 15814,
      "processes" : [
        {
          "activity" : "loadResources",
          "start" : 53,
          "length" : 9
        },
        {
          "activity" : "load",
          "start" : 53,
          "length" : 13
        },
        {
          "activity" : "generateSnapshots",
          "start" : 54,
          "length" : 13
        },
        {
          "activity" : "generateNarratives",
          "start" : 58,
          "length" : 18
        },
        {
          "activity" : "validate",
          "start" : 62,
          "length" : 370
        },
        {
          "activity" : "generate1",
          "start" : 110,
          "length" : 168
        },
        {
          "activity" : "generate2",
          "start" : 121,
          "length" : 191
        },
        {
          "activity" : "generate2",
          "start" : 144,
          "length" : 213
        },
        {
          "activity" : "generateValidationPack",
          "start" : 174,
          "length" : 5
        }
      ]
    },
    {
      "name" : "fsh-generated/resources/StructureDefinition-PersonneStructure.json",
      "size" : 7282,
      "processes" : [
        {
          "activity" : "loadResources",
          "start" : 53,
          "length" : 9
        },
        {
          "activity" : "load",
          "start" : 53,
          "length" : 22
        },
        {
          "activity" : "generateSnapshots",
          "start" : 54,
          "length" : 10
        },
        {
          "activity" : "generateNarratives",
          "start" : 58,
          "length" : 12
        },
        {
          "activity" : "validate",
          "start" : 62,
          "length" : 192
        },
        {
          "activity" : "generate1",
          "start" : 110,
          "length" : 105
        },
        {
          "activity" : "generate2",
          "start" : 122,
          "length" : 128
        },
        {
          "activity" : "generate2",
          "start" : 145,
          "length" : 110
        },
        {
          "activity" : "generateValidationPack",
          "start" : 174,
          "length" : 4
        }
      ]
    },
    {
      "name" : "fsh-generated/resources/StructureDefinition-PersonneStructureAuteur.json",
      "size" : 7454,
      "processes" : [
        {
          "activity" : "loadResources",
          "start" : 53,
          "length" : 9
        },
        {
          "activity" : "load",
          "start" : 53,
          "length" : 23
        },
        {
          "activity" : "generateSnapshots",
          "start" : 54,
          "length" : 9
        },
        {
          "activity" : "generateNarratives",
          "start" : 58,
          "length" : 14
        },
        {
          "activity" : "validate",
          "start" : 63,
          "length" : 248
        },
        {
          "activity" : "generate1",
          "start" : 110,
          "length" : 72
        },
        {
          "activity" : "generate2",
          "start" : 122,
          "length" : 124
        },
        {
          "activity" : "generate2",
          "start" : 145,
          "length" : 80
        },
        {
          "activity" : "generateValidationPack",
          "start" : 174,
          "length" : 3
        }
      ]
    },
    {
      "name" : "fsh-generated/resources/StructureDefinition-Prescription.json",
      "size" : 1872,
      "processes" : [
        {
          "activity" : "loadResources",
          "start" : 53,
          "length" : 8
        },
        {
          "activity" : "load",
          "start" : 53,
          "length" : 20
        },
        {
          "activity" : "generateSnapshots",
          "start" : 54,
          "length" : 6
        },
        {
          "activity" : "generateNarratives",
          "start" : 58,
          "length" : 10
        },
        {
          "activity" : "validate",
          "start" : 63,
          "length" : 56
        },
        {
          "activity" : "generate1",
          "start" : 110,
          "length" : 31
        },
        {
          "activity" : "generate2",
          "start" : 122,
          "length" : 65
        },
        {
          "activity" : "generate2",
          "start" : 145,
          "length" : 32
        }
      ]
    },
    {
      "name" : "fsh-generated/resources/StructureDefinition-PriseEncharge.json",
      "size" : 8837,
      "processes" : [
        {
          "activity" : "loadResources",
          "start" : 53,
          "length" : 9
        },
        {
          "activity" : "load",
          "start" : 53,
          "length" : 23
        },
        {
          "activity" : "generateSnapshots",
          "start" : 55,
          "length" : 9
        },
        {
          "activity" : "generateNarratives",
          "start" : 58,
          "length" : 14
        },
        {
          "activity" : "validate",
          "start" : 63,
          "length" : 119
        },
        {
          "activity" : "generate1",
          "start" : 110,
          "length" : 76
        },
        {
          "activity" : "generate2",
          "start" : 122,
          "length" : 105
        },
        {
          "activity" : "generate2",
          "start" : 145,
          "length" : 165
        },
        {
          "activity" : "generateValidationPack",
          "start" : 174,
          "length" : 2
        }
      ]
    },
    {
      "name" : "fsh-generated/resources/StructureDefinition-Responsable.json",
      "size" : 2749,
      "processes" : [
        {
          "activity" : "loadResources",
          "start" : 53,
          "length" : 9
        },
        {
          "activity" : "load",
          "start" : 53,
          "length" : 11
        },
        {
          "activity" : "generateSnapshots",
          "start" : 55,
          "length" : 6
        },
        {
          "activity" : "generateNarratives",
          "start" : 58,
          "length" : 10
        },
        {
          "activity" : "validate",
          "start" : 63,
          "length" : 55
        },
        {
          "activity" : "generate1",
          "start" : 110,
          "length" : 32
        },
        {
          "activity" : "generate2",
          "start" : 122,
          "length" : 72
        },
        {
          "activity" : "generate2",
          "start" : 145,
          "length" : 30
        },
        {
          "activity" : "generateValidationPack",
          "start" : 174,
          "length" : 1
        }
      ]
    },
    {
      "name" : "fsh-generated/resources/StructureDefinition-StructureConservation.json",
      "size" : 3126,
      "processes" : [
        {
          "activity" : "loadResources",
          "start" : 53,
          "length" : 9
        },
        {
          "activity" : "load",
          "start" : 53,
          "length" : 10
        },
        {
          "activity" : "generateSnapshots",
          "start" : 55,
          "length" : 7
        },
        {
          "activity" : "load-configure",
          "start" : 57,
          "length" : 1
        },
        {
          "activity" : "generateNarratives",
          "start" : 58,
          "length" : 14
        },
        {
          "activity" : "validate",
          "start" : 63,
          "length" : 51
        },
        {
          "activity" : "generate1",
          "start" : 110,
          "length" : 39
        },
        {
          "activity" : "generate2",
          "start" : 122,
          "length" : 73
        },
        {
          "activity" : "generate2",
          "start" : 145,
          "length" : 40
        },
        {
          "activity" : "generateValidationPack",
          "start" : 174,
          "length" : 1
        },
        {
          "activity" : "scanExamplesForR5",
          "start" : 207,
          "length" : 2
        }
      ]
    },
    {
      "name" : "fsh-generated/resources/StructureDefinition-SystemeStructureAuteur.json",
      "size" : 4912,
      "processes" : [
        {
          "activity" : "loadResources",
          "start" : 53,
          "length" : 13
        },
        {
          "activity" : "load",
          "start" : 53,
          "length" : 10
        },
        {
          "activity" : "generateSnapshots",
          "start" : 55,
          "length" : 8
        },
        {
          "activity" : "generateNarratives",
          "start" : 58,
          "length" : 12
        },
        {
          "activity" : "validate",
          "start" : 63,
          "length" : 80
        },
        {
          "activity" : "generate1",
          "start" : 110,
          "length" : 54
        },
        {
          "activity" : "generate2",
          "start" : 122,
          "length" : 81
        },
        {
          "activity" : "generate2",
          "start" : 145,
          "length" : 64
        },
        {
          "activity" : "generateValidationPack",
          "start" : 174,
          "length" : 2
        }
      ]
    },
    {
      "name" : "fsh-generated/resources/StructureDefinition-Validateur.json",
      "size" : 2205,
      "processes" : [
        {
          "activity" : "loadResources",
          "start" : 53,
          "length" : 13
        },
        {
          "activity" : "load",
          "start" : 53,
          "length" : 11
        },
        {
          "activity" : "generateSnapshots",
          "start" : 55,
          "length" : 6
        },
        {
          "activity" : "generateNarratives",
          "start" : 58,
          "length" : 9
        },
        {
          "activity" : "validate",
          "start" : 63,
          "length" : 34
        },
        {
          "activity" : "checkConformanceResources",
          "start" : 109,
          "length" : 1
        },
        {
          "activity" : "generate1",
          "start" : 110,
          "length" : 31
        },
        {
          "activity" : "generate2",
          "start" : 122,
          "length" : 62
        },
        {
          "activity" : "generate2",
          "start" : 145,
          "length" : 29
        },
        {
          "activity" : "generateValidationPack",
          "start" : 174,
          "length" : 1
        }
      ]
    },
    {
      "name" : "fsh-generated/resources/StructureDefinition-fr-author-time.json",
      "size" : 1441,
      "processes" : [
        {
          "activity" : "loadResources",
          "start" : 53,
          "length" : 9
        },
        {
          "activity" : "load",
          "start" : 53,
          "length" : 10
        },
        {
          "activity" : "generateSnapshots",
          "start" : 55,
          "length" : 10
        },
        {
          "activity" : "generateNarratives",
          "start" : 58,
          "length" : 11
        },
        {
          "activity" : "validate",
          "start" : 63,
          "length" : 76
        },
        {
          "activity" : "generate1",
          "start" : 110,
          "length" : 45
        },
        {
          "activity" : "generate2",
          "start" : 122,
          "length" : 76
        },
        {
          "activity" : "generate2",
          "start" : 145,
          "length" : 41
        },
        {
          "activity" : "generateValidationPack",
          "start" : 174,
          "length" : 2
        }
      ]
    },
    {
      "name" : "fsh-generated/resources/StructureDefinition-fr-bundle-document.json",
      "size" : 6825,
      "processes" : [
        {
          "activity" : "loadResources",
          "start" : 53,
          "length" : 9
        },
        {
          "activity" : "load",
          "start" : 54,
          "length" : 18
        },
        {
          "activity" : "generateSnapshots",
          "start" : 55,
          "length" : 1122
        },
        {
          "activity" : "checkR4R4B",
          "start" : 57,
          "length" : 1
        },
        {
          "activity" : "generateNarratives",
          "start" : 58,
          "length" : 54
        },
        {
          "activity" : "validate",
          "start" : 63,
          "length" : 2521
        },
        {
          "activity" : "scanForUsageStats",
          "start" : 109,
          "length" : 3
        },
        {
          "activity" : "generate1",
          "start" : 110,
          "length" : 629
        },
        {
          "activity" : "generate2",
          "start" : 122,
          "length" : 1990
        },
        {
          "activity" : "generate2",
          "start" : 145,
          "length" : 1164
        },
        {
          "activity" : "generateValidationPack",
          "start" : 174,
          "length" : 22
        },
        {
          "activity" : "scanExamplesForR5",
          "start" : 207,
          "length" : 2
        }
      ]
    },
    {
      "name" : "fsh-generated/resources/StructureDefinition-fr-composition-document.json",
      "size" : 18386,
      "processes" : [
        {
          "activity" : "loadResources",
          "start" : 53,
          "length" : 10
        },
        {
          "activity" : "load",
          "start" : 54,
          "length" : 29
        },
        {
          "activity" : "generateSnapshots",
          "start" : 56,
          "length" : 76
        },
        {
          "activity" : "load-configure",
          "start" : 57,
          "length" : 1
        },
        {
          "activity" : "generateNarratives",
          "start" : 58,
          "length" : 104
        },
        {
          "activity" : "validate",
          "start" : 66,
          "length" : 2493
        },
        {
          "activity" : "scanForUsageStats",
          "start" : 109,
          "length" : 3
        },
        {
          "activity" : "generate1",
          "start" : 111,
          "length" : 549
        },
        {
          "activity" : "generate2",
          "start" : 124,
          "length" : 1283
        },
        {
          "activity" : "generate2",
          "start" : 146,
          "length" : 404
        },
        {
          "activity" : "generateValidationPack",
          "start" : 174,
          "length" : 20
        },
        {
          "activity" : "scanExamplesForR5",
          "start" : 207,
          "length" : 2
        }
      ]
    },
    {
      "name" : "fsh-generated/resources/StructureDefinition-fr-core-assigned-author.json",
      "size" : 6461,
      "processes" : [
        {
          "activity" : "loadResources",
          "start" : 53,
          "length" : 9
        },
        {
          "activity" : "load",
          "start" : 54,
          "length" : 24
        },
        {
          "activity" : "generateSnapshots",
          "start" : 56,
          "length" : 50
        },
        {
          "activity" : "generateNarratives",
          "start" : 58,
          "length" : 14
        },
        {
          "activity" : "validate",
          "start" : 68,
          "length" : 221
        },
        {
          "activity" : "checkConformanceResources",
          "start" : 109,
          "length" : 1
        },
        {
          "activity" : "generate1",
          "start" : 112,
          "length" : 97
        },
        {
          "activity" : "generate2",
          "start" : 126,
          "length" : 110
        },
        {
          "activity" : "generate2",
          "start" : 147,
          "length" : 40
        },
        {
          "activity" : "generateValidationPack",
          "start" : 174,
          "length" : 3
        }
      ]
    },
    {
      "name" : "fsh-generated/resources/StructureDefinition-fr-core-assigned-custodian.json",
      "size" : 2728,
      "processes" : [
        {
          "activity" : "loadResources",
          "start" : 53,
          "length" : 8
        },
        {
          "activity" : "load",
          "start" : 54,
          "length" : 22
        },
        {
          "activity" : "generateSnapshots",
          "start" : 56,
          "length" : 23
        },
        {
          "activity" : "generateNarratives",
          "start" : 58,
          "length" : 11
        },
        {
          "activity" : "validate",
          "start" : 69,
          "length" : 122
        },
        {
          "activity" : "generate1",
          "start" : 112,
          "length" : 47
        },
        {
          "activity" : "generate2",
          "start" : 126,
          "length" : 94
        },
        {
          "activity" : "generate2",
          "start" : 147,
          "length" : 26
        },
        {
          "activity" : "generateValidationPack",
          "start" : 174,
          "length" : 2
        },
        {
          "activity" : "scanProfilesForR5",
          "start" : 207,
          "length" : 1
        }
      ]
    },
    {
      "name" : "fsh-generated/resources/StructureDefinition-fr-core-assigned-entity.json",
      "size" : 6138,
      "processes" : [
        {
          "activity" : "loadResources",
          "start" : 53,
          "length" : 9
        },
        {
          "activity" : "load",
          "start" : 54,
          "length" : 22
        },
        {
          "activity" : "generateSnapshots",
          "start" : 56,
          "length" : 24
        },
        {
          "activity" : "generateNarratives",
          "start" : 58,
          "length" : 17
        },
        {
          "activity" : "validate",
          "start" : 69,
          "length" : 289
        },
        {
          "activity" : "generate1",
          "start" : 112,
          "length" : 101
        },
        {
          "activity" : "generate2",
          "start" : 126,
          "length" : 113
        },
        {
          "activity" : "generate2",
          "start" : 147,
          "length" : 53
        },
        {
          "activity" : "generateValidationPack",
          "start" : 174,
          "length" : 4
        }
      ]
    },
    {
      "name" : "fsh-generated/resources/StructureDefinition-fr-core-associated-entity.json",
      "size" : 5034,
      "processes" : [
        {
          "activity" : "loadResources",
          "start" : 53,
          "length" : 9
        },
        {
          "activity" : "load",
          "start" : 54,
          "length" : 22
        },
        {
          "activity" : "generateSnapshots",
          "start" : 56,
          "length" : 50
        },
        {
          "activity" : "generateNarratives",
          "start" : 58,
          "length" : 14
        },
        {
          "activity" : "validate",
          "start" : 69,
          "length" : 183
        },
        {
          "activity" : "generate1",
          "start" : 112,
          "length" : 79
        },
        {
          "activity" : "generate2",
          "start" : 126,
          "length" : 96
        },
        {
          "activity" : "generate2",
          "start" : 147,
          "length" : 37
        },
        {
          "activity" : "generateValidationPack",
          "start" : 174,
          "length" : 2
        }
      ]
    },
    {
      "name" : "fsh-generated/resources/StructureDefinition-fr-core-authenticator.json",
      "size" : 3875,
      "processes" : [
        {
          "activity" : "loadResources",
          "start" : 53,
          "length" : 8
        },
        {
          "activity" : "load",
          "start" : 54,
          "length" : 21
        },
        {
          "activity" : "generateSnapshots",
          "start" : 56,
          "length" : 24
        },
        {
          "activity" : "generateNarratives",
          "start" : 58,
          "length" : 13
        },
        {
          "activity" : "validate",
          "start" : 69,
          "length" : 232
        },
        {
          "activity" : "generate1",
          "start" : 112,
          "length" : 74
        },
        {
          "activity" : "generate2",
          "start" : 126,
          "length" : 129
        },
        {
          "activity" : "generate2",
          "start" : 147,
          "length" : 47
        },
        {
          "activity" : "generateValidationPack",
          "start" : 174,
          "length" : 3
        }
      ]
    },
    {
      "name" : "fsh-generated/resources/StructureDefinition-fr-core-author.json",
      "size" : 4287,
      "processes" : [
        {
          "activity" : "loadResources",
          "start" : 53,
          "length" : 9
        },
        {
          "activity" : "load",
          "start" : 54,
          "length" : 21
        },
        {
          "activity" : "generateSnapshots",
          "start" : 56,
          "length" : 23
        },
        {
          "activity" : "generateNarratives",
          "start" : 58,
          "length" : 15
        },
        {
          "activity" : "validate",
          "start" : 69,
          "length" : 222
        },
        {
          "activity" : "scanForUsageStats",
          "start" : 109,
          "length" : 1
        },
        {
          "activity" : "generate1",
          "start" : 112,
          "length" : 83
        },
        {
          "activity" : "generate2",
          "start" : 126,
          "length" : 167
        },
        {
          "activity" : "generate2",
          "start" : 147,
          "length" : 42
        },
        {
          "activity" : "generateValidationPack",
          "start" : 174,
          "length" : 2
        }
      ]
    },
    {
      "name" : "fsh-generated/resources/StructureDefinition-fr-core-authoring-device.json",
      "size" : 2658,
      "processes" : [
        {
          "activity" : "loadResources",
          "start" : 53,
          "length" : 8
        },
        {
          "activity" : "load",
          "start" : 54,
          "length" : 21
        },
        {
          "activity" : "generateSnapshots",
          "start" : 56,
          "length" : 14
        },
        {
          "activity" : "load-configure",
          "start" : 57,
          "length" : 1
        },
        {
          "activity" : "generateNarratives",
          "start" : 58,
          "length" : 13
        },
        {
          "activity" : "validate",
          "start" : 70,
          "length" : 145
        },
        {
          "activity" : "generate1",
          "start" : 112,
          "length" : 52
        },
        {
          "activity" : "generate2",
          "start" : 126,
          "length" : 142
        },
        {
          "activity" : "generate2",
          "start" : 147,
          "length" : 29
        },
        {
          "activity" : "generateValidationPack",
          "start" : 174,
          "length" : 2
        }
      ]
    },
    {
      "name" : "fsh-generated/resources/StructureDefinition-fr-core-authorization.json",
      "size" : 3187,
      "processes" : [
        {
          "activity" : "loadResources",
          "start" : 53,
          "length" : 8
        },
        {
          "activity" : "load",
          "start" : 54,
          "length" : 20
        },
        {
          "activity" : "generateSnapshots",
          "start" : 56,
          "length" : 23
        },
        {
          "activity" : "generateNarratives",
          "start" : 58,
          "length" : 27
        },
        {
          "activity" : "validate",
          "start" : 70,
          "length" : 306
        },
        {
          "activity" : "generate1",
          "start" : 112,
          "length" : 75
        },
        {
          "activity" : "generate2",
          "start" : 126,
          "length" : 174
        },
        {
          "activity" : "generate2",
          "start" : 147,
          "length" : 57
        },
        {
          "activity" : "generateValidationPack",
          "start" : 174,
          "length" : 2
        }
      ]
    },
    {
      "name" : "fsh-generated/resources/StructureDefinition-fr-core-clinical-document.json",
      "size" : 10147,
      "processes" : [
        {
          "activity" : "loadResources",
          "start" : 53,
          "length" : 9
        },
        {
          "activity" : "load",
          "start" : 54,
          "length" : 14
        },
        {
          "activity" : "generateSnapshots",
          "start" : 56,
          "length" : 173
        },
        {
          "activity" : "generateNarratives",
          "start" : 58,
          "length" : 30
        },
        {
          "activity" : "validate",
          "start" : 70,
          "length" : 253
        },
        {
          "activity" : "generate1",
          "start" : 112,
          "length" : 111
        },
        {
          "activity" : "generate2",
          "start" : 127,
          "length" : 171
        },
        {
          "activity" : "generate2",
          "start" : 147,
          "length" : 49
        },
        {
          "activity" : "generateValidationPack",
          "start" : 174,
          "length" : 3
        },
        {
          "activity" : "scanExamplesForR5",
          "start" : 207,
          "length" : 1
        }
      ]
    },
    {
      "name" : "fsh-generated/resources/StructureDefinition-fr-core-component-of.json",
      "size" : 2672,
      "processes" : [
        {
          "activity" : "loadResources",
          "start" : 53,
          "length" : 8
        },
        {
          "activity" : "load",
          "start" : 54,
          "length" : 10
        },
        {
          "activity" : "generateSnapshots",
          "start" : 56,
          "length" : 48
        },
        {
          "activity" : "generateNarratives",
          "start" : 58,
          "length" : 19
        },
        {
          "activity" : "validate",
          "start" : 70,
          "length" : 122
        },
        {
          "activity" : "generate1",
          "start" : 112,
          "length" : 52
        },
        {
          "activity" : "generate2",
          "start" : 127,
          "length" : 113
        },
        {
          "activity" : "generate2",
          "start" : 147,
          "length" : 25
        },
        {
          "activity" : "makeDependencies",
          "start" : 157,
          "length" : 1
        },
        {
          "activity" : "generateValidationPack",
          "start" : 174,
          "length" : 2
        }
      ]
    },
    {
      "name" : "fsh-generated/resources/StructureDefinition-fr-core-custodian.json",
      "size" : 2613,
      "processes" : [
        {
          "activity" : "loadResources",
          "start" : 53,
          "length" : 8
        },
        {
          "activity" : "load",
          "start" : 54,
          "length" : 10
        },
        {
          "activity" : "generateSnapshots",
          "start" : 56,
          "length" : 8
        },
        {
          "activity" : "generateNarratives",
          "start" : 58,
          "length" : 16
        },
        {
          "activity" : "validate",
          "start" : 70,
          "length" : 128
        },
        {
          "activity" : "generate1",
          "start" : 112,
          "length" : 48
        },
        {
          "activity" : "generate2",
          "start" : 127,
          "length" : 114
        },
        {
          "activity" : "generate2",
          "start" : 147,
          "length" : 25
        },
        {
          "activity" : "generateValidationPack",
          "start" : 174,
          "length" : 2
        }
      ]
    },
    {
      "name" : "fsh-generated/resources/StructureDefinition-fr-core-data-enterer.json",
      "size" : 3194,
      "processes" : [
        {
          "activity" : "loadResources",
          "start" : 53,
          "length" : 8
        },
        {
          "activity" : "load",
          "start" : 54,
          "length" : 21
        },
        {
          "activity" : "generateSnapshots",
          "start" : 56,
          "length" : 7
        },
        {
          "activity" : "generateNarratives",
          "start" : 58,
          "length" : 12
        },
        {
          "activity" : "validate",
          "start" : 71,
          "length" : 129
        },
        {
          "activity" : "generate1",
          "start" : 112,
          "length" : 58
        },
        {
          "activity" : "generate2",
          "start" : 127,
          "length" : 116
        },
        {
          "activity" : "generate2",
          "start" : 147,
          "length" : 28
        },
        {
          "activity" : "generateValidationPack",
          "start" : 174,
          "length" : 2
        }
      ]
    },
    {
      "name" : "fsh-generated/resources/StructureDefinition-fr-core-documentation-of.json",
      "size" : 2900,
      "processes" : [
        {
          "activity" : "loadResources",
          "start" : 53,
          "length" : 8
        },
        {
          "activity" : "load",
          "start" : 54,
          "length" : 18
        },
        {
          "activity" : "generateSnapshots",
          "start" : 56,
          "length" : 11
        },
        {
          "activity" : "generateNarratives",
          "start" : 58,
          "length" : 11
        },
        {
          "activity" : "validate",
          "start" : 71,
          "length" : 113
        },
        {
          "activity" : "generate1",
          "start" : 112,
          "length" : 49
        },
        {
          "activity" : "generate2",
          "start" : 127,
          "length" : 108
        },
        {
          "activity" : "generate2",
          "start" : 147,
          "length" : 24
        },
        {
          "activity" : "generateValidationPack",
          "start" : 174,
          "length" : 2
        }
      ]
    },
    {
      "name" : "fsh-generated/resources/StructureDefinition-fr-core-encompassing-encounter.json",
      "size" : 7293,
      "processes" : [
        {
          "activity" : "loadResources",
          "start" : 53,
          "length" : 9
        },
        {
          "activity" : "load",
          "start" : 54,
          "length" : 11
        },
        {
          "activity" : "generateSnapshots",
          "start" : 56,
          "length" : 16
        },
        {
          "activity" : "generateNarratives",
          "start" : 58,
          "length" : 19
        },
        {
          "activity" : "validate",
          "start" : 71,
          "length" : 331
        },
        {
          "activity" : "scanForUsageStats",
          "start" : 109,
          "length" : 1
        },
        {
          "activity" : "generate1",
          "start" : 113,
          "length" : 138
        },
        {
          "activity" : "generate2",
          "start" : 127,
          "length" : 205
        },
        {
          "activity" : "generate2",
          "start" : 147,
          "length" : 63
        },
        {
          "activity" : "generateValidationPack",
          "start" : 174,
          "length" : 4
        }
      ]
    },
    {
      "name" : "fsh-generated/resources/StructureDefinition-fr-core-encounter-participant.json",
      "size" : 3078,
      "processes" : [
        {
          "activity" : "loadResources",
          "start" : 53,
          "length" : 8
        },
        {
          "activity" : "load",
          "start" : 54,
          "length" : 9
        },
        {
          "activity" : "generateSnapshots",
          "start" : 56,
          "length" : 12
        },
        {
          "activity" : "load-configure",
          "start" : 57,
          "length" : 1
        },
        {
          "activity" : "generateNarratives",
          "start" : 58,
          "length" : 11
        },
        {
          "activity" : "validate",
          "start" : 71,
          "length" : 121
        },
        {
          "activity" : "generate1",
          "start" : 113,
          "length" : 51
        },
        {
          "activity" : "generate2",
          "start" : 127,
          "length" : 119
        },
        {
          "activity" : "generate2",
          "start" : 147,
          "length" : 26
        },
        {
          "activity" : "generateValidationPack",
          "start" : 174,
          "length" : 1
        }
      ]
    },
    {
      "name" : "fsh-generated/resources/StructureDefinition-fr-core-health-care-facility.json",
      "size" : 5645,
      "processes" : [
        {
          "activity" : "loadResources",
          "start" : 53,
          "length" : 8
        },
        {
          "activity" : "load",
          "start" : 54,
          "length" : 14
        },
        {
          "activity" : "generateSnapshots",
          "start" : 56,
          "length" : 17
        },
        {
          "activity" : "generateNarratives",
          "start" : 58,
          "length" : 17
        },
        {
          "activity" : "validate",
          "start" : 71,
          "length" : 261
        },
        {
          "activity" : "generate1",
          "start" : 113,
          "length" : 105
        },
        {
          "activity" : "generate2",
          "start" : 128,
          "length" : 179
        },
        {
          "activity" : "generate2",
          "start" : 147,
          "length" : 51
        },
        {
          "activity" : "generateValidationPack",
          "start" : 174,
          "length" : 4
        }
      ]
    },
    {
      "name" : "fsh-generated/resources/StructureDefinition-fr-core-inFulfillment-of.json",
      "size" : 2537,
      "processes" : [
        {
          "activity" : "loadResources",
          "start" : 53,
          "length" : 8
        },
        {
          "activity" : "load",
          "start" : 54,
          "length" : 10
        },
        {
          "activity" : "generateSnapshots",
          "start" : 56,
          "length" : 9
        },
        {
          "activity" : "generateNarratives",
          "start" : 58,
          "length" : 10
        },
        {
          "activity" : "validate",
          "start" : 72,
          "length" : 147
        },
        {
          "activity" : "generate1",
          "start" : 113,
          "length" : 46
        },
        {
          "activity" : "generate2",
          "start" : 128,
          "length" : 108
        },
        {
          "activity" : "generate2",
          "start" : 147,
          "length" : 25
        },
        {
          "activity" : "generateValidationPack",
          "start" : 174,
          "length" : 2
        }
      ]
    },
    {
      "name" : "fsh-generated/resources/StructureDefinition-fr-core-informant.json",
      "size" : 3536,
      "processes" : [
        {
          "activity" : "loadResources",
          "start" : 53,
          "length" : 8
        },
        {
          "activity" : "load",
          "start" : 54,
          "length" : 9
        },
        {
          "activity" : "generateSnapshots",
          "start" : 56,
          "length" : 8
        },
        {
          "activity" : "generateNarratives",
          "start" : 58,
          "length" : 10
        },
        {
          "activity" : "validate",
          "start" : 72,
          "length" : 123
        },
        {
          "activity" : "generate1",
          "start" : 113,
          "length" : 55
        },
        {
          "activity" : "generate2",
          "start" : 128,
          "length" : 120
        },
        {
          "activity" : "generate2",
          "start" : 148,
          "length" : 30
        },
        {
          "activity" : "generateValidationPack",
          "start" : 174,
          "length" : 1
        }
      ]
    },
    {
      "name" : "fsh-generated/resources/StructureDefinition-fr-core-information-recipient.json",
      "size" : 2865,
      "processes" : [
        {
          "activity" : "loadResources",
          "start" : 53,
          "length" : 9
        },
        {
          "activity" : "load",
          "start" : 54,
          "length" : 10
        },
        {
          "activity" : "generateSnapshots",
          "start" : 56,
          "length" : 7
        },
        {
          "activity" : "generateNarratives",
          "start" : 58,
          "length" : 11
        },
        {
          "activity" : "validate",
          "start" : 72,
          "length" : 109
        },
        {
          "activity" : "generate1",
          "start" : 113,
          "length" : 51
        },
        {
          "activity" : "generate2",
          "start" : 128,
          "length" : 113
        },
        {
          "activity" : "generate2",
          "start" : 148,
          "length" : 26
        },
        {
          "activity" : "generateValidationPack",
          "start" : 174,
          "length" : 1
        }
      ]
    },
    {
      "name" : "fsh-generated/resources/StructureDefinition-fr-core-intended-recipient.json",
      "size" : 4901,
      "processes" : [
        {
          "activity" : "loadResources",
          "start" : 53,
          "length" : 9
        },
        {
          "activity" : "load",
          "start" : 54,
          "length" : 10
        },
        {
          "activity" : "generateSnapshots",
          "start" : 56,
          "length" : 12
        },
        {
          "activity" : "generateNarratives",
          "start" : 58,
          "length" : 19
        },
        {
          "activity" : "validate",
          "start" : 72,
          "length" : 335
        },
        {
          "activity" : "generate1",
          "start" : 113,
          "length" : 105
        },
        {
          "activity" : "generate2",
          "start" : 128,
          "length" : 219
        },
        {
          "activity" : "generate2",
          "start" : 148,
          "length" : 66
        },
        {
          "activity" : "generateValidationPack",
          "start" : 174,
          "length" : 3
        },
        {
          "activity" : "scanExamplesForR5",
          "start" : 207,
          "length" : 1
        }
      ]
    },
    {
      "name" : "fsh-generated/resources/StructureDefinition-fr-core-legal-authenticator.json",
      "size" : 4414,
      "processes" : [
        {
          "activity" : "loadResources",
          "start" : 53,
          "length" : 8
        },
        {
          "activity" : "load",
          "start" : 54,
          "length" : 10
        },
        {
          "activity" : "generateSnapshots",
          "start" : 56,
          "length" : 19
        },
        {
          "activity" : "generateNarratives",
          "start" : 58,
          "length" : 14
        },
        {
          "activity" : "validate",
          "start" : 72,
          "length" : 416
        },
        {
          "activity" : "checkConformanceResources",
          "start" : 109,
          "length" : 1
        },
        {
          "activity" : "scanForUsageStats",
          "start" : 109,
          "length" : 1
        },
        {
          "activity" : "generate1",
          "start" : 113,
          "length" : 103
        },
        {
          "activity" : "generate2",
          "start" : 128,
          "length" : 204
        },
        {
          "activity" : "generate2",
          "start" : 148,
          "length" : 71
        },
        {
          "activity" : "generateValidationPack",
          "start" : 174,
          "length" : 4
        }
      ]
    },
    {
      "name" : "fsh-generated/resources/StructureDefinition-fr-core-name.json",
      "size" : 2196,
      "processes" : [
        {
          "activity" : "loadResources",
          "start" : 53,
          "length" : 9
        },
        {
          "activity" : "load",
          "start" : 54,
          "length" : 10
        },
        {
          "activity" : "generateSnapshots",
          "start" : 56,
          "length" : 14
        },
        {
          "activity" : "generateNarratives",
          "start" : 58,
          "length" : 9
        },
        {
          "activity" : "validate",
          "start" : 73,
          "length" : 97
        },
        {
          "activity" : "generate1",
          "start" : 113,
          "length" : 44
        },
        {
          "activity" : "generate2",
          "start" : 128,
          "length" : 102
        },
        {
          "activity" : "generate2",
          "start" : 148,
          "length" : 20
        },
        {
          "activity" : "generateValidationPack",
          "start" : 174,
          "length" : 1
        }
      ]
    },
    {
      "name" : "fsh-generated/resources/StructureDefinition-fr-core-order.json",
      "size" : 3562,
      "processes" : [
        {
          "activity" : "loadResources",
          "start" : 53,
          "length" : 8
        },
        {
          "activity" : "load",
          "start" : 54,
          "length" : 10
        },
        {
          "activity" : "generateSnapshots",
          "start" : 56,
          "length" : 15
        },
        {
          "activity" : "load-configure",
          "start" : 57,
          "length" : 1
        },
        {
          "activity" : "generateNarratives",
          "start" : 58,
          "length" : 12
        },
        {
          "activity" : "validate",
          "start" : 73,
          "length" : 162
        },
        {
          "activity" : "generate1",
          "start" : 113,
          "length" : 72
        },
        {
          "activity" : "generate2",
          "start" : 129,
          "length" : 82
        },
        {
          "activity" : "generate2",
          "start" : 148,
          "length" : 31
        },
        {
          "activity" : "generateValidationPack",
          "start" : 174,
          "length" : 2
        },
        {
          "activity" : "scanProfilesForR5",
          "start" : 207,
          "length" : 1
        }
      ]
    },
    {
      "name" : "fsh-generated/resources/StructureDefinition-fr-core-parent-document.json",
      "size" : 2634,
      "processes" : [
        {
          "activity" : "loadResources",
          "start" : 53,
          "length" : 9
        },
        {
          "activity" : "load",
          "start" : 54,
          "length" : 18
        },
        {
          "activity" : "generateSnapshots",
          "start" : 56,
          "length" : 15
        },
        {
          "activity" : "generateNarratives",
          "start" : 58,
          "length" : 10
        },
        {
          "activity" : "validate",
          "start" : 73,
          "length" : 165
        },
        {
          "activity" : "generate1",
          "start" : 113,
          "length" : 57
        },
        {
          "activity" : "generate2",
          "start" : 129,
          "length" : 86
        },
        {
          "activity" : "generate2",
          "start" : 148,
          "length" : 32
        },
        {
          "activity" : "generateValidationPack",
          "start" : 174,
          "length" : 1
        }
      ]
    },
    {
      "name" : "fsh-generated/resources/StructureDefinition-fr-core-participant.json",
      "size" : 5151,
      "processes" : [
        {
          "activity" : "loadResources",
          "start" : 53,
          "length" : 9
        },
        {
          "activity" : "load",
          "start" : 54,
          "length" : 10
        },
        {
          "activity" : "generateSnapshots",
          "start" : 56,
          "length" : 16
        },
        {
          "activity" : "generateNarratives",
          "start" : 59,
          "length" : 14
        },
        {
          "activity" : "validate",
          "start" : 73,
          "length" : 221
        },
        {
          "activity" : "generate1",
          "start" : 113,
          "length" : 102
        },
        {
          "activity" : "generate2",
          "start" : 129,
          "length" : 101
        },
        {
          "activity" : "generate2",
          "start" : 148,
          "length" : 41
        },
        {
          "activity" : "generateValidationPack",
          "start" : 174,
          "length" : 3
        }
      ]
    },
    {
      "name" : "fsh-generated/resources/StructureDefinition-fr-core-patient-role.json",
      "size" : 3967,
      "processes" : [
        {
          "activity" : "loadResources",
          "start" : 53,
          "length" : 8
        },
        {
          "activity" : "load",
          "start" : 54,
          "length" : 10
        },
        {
          "activity" : "generateSnapshots",
          "start" : 56,
          "length" : 15
        },
        {
          "activity" : "generateNarratives",
          "start" : 59,
          "length" : 13
        },
        {
          "activity" : "validate",
          "start" : 73,
          "length" : 146
        },
        {
          "activity" : "generate1",
          "start" : 113,
          "length" : 74
        },
        {
          "activity" : "generate2",
          "start" : 129,
          "length" : 74
        },
        {
          "activity" : "generate2",
          "start" : 148,
          "length" : 32
        },
        {
          "activity" : "generateValidationPack",
          "start" : 174,
          "length" : 2
        }
      ]
    },
    {
      "name" : "fsh-generated/resources/StructureDefinition-fr-core-patient.json",
      "size" : 4703,
      "processes" : [
        {
          "activity" : "loadResources",
          "start" : 53,
          "length" : 9
        },
        {
          "activity" : "load",
          "start" : 54,
          "length" : 10
        },
        {
          "activity" : "generateSnapshots",
          "start" : 56,
          "length" : 16
        },
        {
          "activity" : "generateNarratives",
          "start" : 59,
          "length" : 17
        },
        {
          "activity" : "validate",
          "start" : 73,
          "length" : 289
        },
        {
          "activity" : "scanForUsageStats",
          "start" : 109,
          "length" : 1
        },
        {
          "activity" : "validate",
          "start" : 109,
          "length" : 1
        },
        {
          "activity" : "generate1",
          "start" : 114,
          "length" : 98
        },
        {
          "activity" : "generate2",
          "start" : 129,
          "length" : 102
        },
        {
          "activity" : "generate2",
          "start" : 148,
          "length" : 56
        },
        {
          "activity" : "generateValidationPack",
          "start" : 174,
          "length" : 3
        },
        {
          "activity" : "scanExamplesForR5",
          "start" : 207,
          "length" : 1
        }
      ]
    },
    {
      "name" : "fsh-generated/resources/StructureDefinition-fr-core-performer.json",
      "size" : 3199,
      "processes" : [
        {
          "activity" : "loadResources",
          "start" : 53,
          "length" : 9
        },
        {
          "activity" : "load",
          "start" : 53,
          "length" : 1
        },
        {
          "activity" : "load",
          "start" : 54,
          "length" : 10
        },
        {
          "activity" : "generateSnapshots",
          "start" : 56,
          "length" : 17
        },
        {
          "activity" : "generateNarratives",
          "start" : 59,
          "length" : 15
        },
        {
          "activity" : "validate",
          "start" : 74,
          "length" : 282
        },
        {
          "activity" : "generate1",
          "start" : 114,
          "length" : 82
        },
        {
          "activity" : "generate2",
          "start" : 129,
          "length" : 108
        },
        {
          "activity" : "generate2",
          "start" : 148,
          "length" : 54
        },
        {
          "activity" : "generateValidationPack",
          "start" : 174,
          "length" : 2
        }
      ]
    },
    {
      "name" : "fsh-generated/resources/StructureDefinition-fr-core-person.json",
      "size" : 3787,
      "processes" : [
        {
          "activity" : "loadResources",
          "start" : 53,
          "length" : 9
        },
        {
          "activity" : "load",
          "start" : 54,
          "length" : 10
        },
        {
          "activity" : "generateSnapshots",
          "start" : 56,
          "length" : 15
        },
        {
          "activity" : "generateNarratives",
          "start" : 59,
          "length" : 14
        },
        {
          "activity" : "validate",
          "start" : 74,
          "length" : 223
        },
        {
          "activity" : "validate",
          "start" : 109,
          "length" : 1
        },
        {
          "activity" : "generate1",
          "start" : 114,
          "length" : 81
        },
        {
          "activity" : "generate2",
          "start" : 129,
          "length" : 91
        },
        {
          "activity" : "generate2",
          "start" : 148,
          "length" : 48
        },
        {
          "activity" : "generateValidationPack",
          "start" : 174,
          "length" : 2
        }
      ]
    },
    {
      "name" : "fsh-generated/resources/StructureDefinition-fr-core-record-target.json",
      "size" : 2799,
      "processes" : [
        {
          "activity" : "loadResources",
          "start" : 53,
          "length" : 9
        },
        {
          "activity" : "load",
          "start" : 54,
          "length" : 10
        },
        {
          "activity" : "generateSnapshots",
          "start" : 56,
          "length" : 14
        },
        {
          "activity" : "generateNarratives",
          "start" : 59,
          "length" : 12
        },
        {
          "activity" : "validate",
          "start" : 74,
          "length" : 110
        },
        {
          "activity" : "generate1",
          "start" : 114,
          "length" : 51
        },
        {
          "activity" : "generate2",
          "start" : 129,
          "length" : 70
        },
        {
          "activity" : "generate2",
          "start" : 148,
          "length" : 26
        },
        {
          "activity" : "generateValidationPack",
          "start" : 174,
          "length" : 2
        }
      ]
    },
    {
      "name" : "fsh-generated/resources/StructureDefinition-fr-core-related-document.json",
      "size" : 2929,
      "processes" : [
        {
          "activity" : "loadResources",
          "start" : 53,
          "length" : 8
        },
        {
          "activity" : "load",
          "start" : 54,
          "length" : 10
        },
        {
          "activity" : "generateSnapshots",
          "start" : 56,
          "length" : 12
        },
        {
          "activity" : "generateNarratives",
          "start" : 59,
          "length" : 17
        },
        {
          "activity" : "validate",
          "start" : 74,
          "length" : 100
        },
        {
          "activity" : "generate1",
          "start" : 114,
          "length" : 48
        },
        {
          "activity" : "generate2",
          "start" : 129,
          "length" : 68
        },
        {
          "activity" : "generate2",
          "start" : 148,
          "length" : 25
        },
        {
          "activity" : "generateValidationPack",
          "start" : 174,
          "length" : 2
        }
      ]
    },
    {
      "name" : "fsh-generated/resources/StructureDefinition-fr-core-related-entity.json",
      "size" : 4380,
      "processes" : [
        {
          "activity" : "loadResources",
          "start" : 53,
          "length" : 9
        },
        {
          "activity" : "load",
          "start" : 54,
          "length" : 9
        },
        {
          "activity" : "generateSnapshots",
          "start" : 56,
          "length" : 8
        },
        {
          "activity" : "generateNarratives",
          "start" : 59,
          "length" : 17
        },
        {
          "activity" : "validate",
          "start" : 74,
          "length" : 181
        },
        {
          "activity" : "generate1",
          "start" : 114,
          "length" : 84
        },
        {
          "activity" : "generate2",
          "start" : 129,
          "length" : 139
        },
        {
          "activity" : "generate2",
          "start" : 148,
          "length" : 35
        },
        {
          "activity" : "generateValidationPack",
          "start" : 174,
          "length" : 2
        }
      ]
    },
    {
      "name" : "fsh-generated/resources/StructureDefinition-fr-core-represented-custodian-organization.json",
      "size" : 4372,
      "processes" : [
        {
          "activity" : "loadResources",
          "start" : 53,
          "length" : 10
        },
        {
          "activity" : "load",
          "start" : 54,
          "length" : 11
        },
        {
          "activity" : "generateSnapshots",
          "start" : 56,
          "length" : 7
        },
        {
          "activity" : "load-configure",
          "start" : 57,
          "length" : 1
        },
        {
          "activity" : "generateNarratives",
          "start" : 59,
          "length" : 13
        },
        {
          "activity" : "validate",
          "start" : 75,
          "length" : 158
        },
        {
          "activity" : "generate1",
          "start" : 114,
          "length" : 73
        },
        {
          "activity" : "generate2",
          "start" : 130,
          "length" : 130
        },
        {
          "activity" : "generate2",
          "start" : 148,
          "length" : 33
        },
        {
          "activity" : "generateValidationPack",
          "start" : 174,
          "length" : 3
        }
      ]
    },
    {
      "name" : "fsh-generated/resources/StructureDefinition-fr-core-represented-organization.json",
      "size" : 4531,
      "processes" : [
        {
          "activity" : "loadResources",
          "start" : 53,
          "length" : 8
        },
        {
          "activity" : "load",
          "start" : 54,
          "length" : 10
        },
        {
          "activity" : "generateSnapshots",
          "start" : 56,
          "length" : 9
        },
        {
          "activity" : "generateNarratives",
          "start" : 59,
          "length" : 12
        },
        {
          "activity" : "validate",
          "start" : 75,
          "length" : 192
        },
        {
          "activity" : "scanForUsageStats",
          "start" : 109,
          "length" : 1
        },
        {
          "activity" : "generate1",
          "start" : 114,
          "length" : 78
        },
        {
          "activity" : "generate2",
          "start" : 130,
          "length" : 134
        },
        {
          "activity" : "generate2",
          "start" : 148,
          "length" : 36
        },
        {
          "activity" : "generateValidationPack",
          "start" : 174,
          "length" : 2
        }
      ]
    },
    {
      "name" : "fsh-generated/resources/StructureDefinition-fr-core-service-event.json",
      "size" : 9007,
      "processes" : [
        {
          "activity" : "loadResources",
          "start" : 53,
          "length" : 9
        },
        {
          "activity" : "load",
          "start" : 54,
          "length" : 12
        },
        {
          "activity" : "generateSnapshots",
          "start" : 56,
          "length" : 12
        },
        {
          "activity" : "generateNarratives",
          "start" : 59,
          "length" : 18
        },
        {
          "activity" : "validate",
          "start" : 75,
          "length" : 600
        },
        {
          "activity" : "generate1",
          "start" : 114,
          "length" : 162
        },
        {
          "activity" : "generate2",
          "start" : 130,
          "length" : 301
        },
        {
          "activity" : "generate2",
          "start" : 148,
          "length" : 100
        },
        {
          "activity" : "generateValidationPack",
          "start" : 174,
          "length" : 5
        },
        {
          "activity" : "scanExamplesForR5",
          "start" : 207,
          "length" : 1
        }
      ]
    },
    {
      "name" : "fsh-generated/resources/StructureDefinition-fr-device-document.json",
      "size" : 1672,
      "processes" : [
        {
          "activity" : "loadResources",
          "start" : 53,
          "length" : 9
        },
        {
          "activity" : "load",
          "start" : 54,
          "length" : 10
        },
        {
          "activity" : "generateSnapshots",
          "start" : 57,
          "length" : 18
        },
        {
          "activity" : "generateNarratives",
          "start" : 59,
          "length" : 20
        },
        {
          "activity" : "validate",
          "start" : 76,
          "length" : 986
        },
        {
          "activity" : "scanForUsageStats",
          "start" : 109,
          "length" : 1
        },
        {
          "activity" : "generate1",
          "start" : 114,
          "length" : 202
        },
        {
          "activity" : "generate2",
          "start" : 130,
          "length" : 572
        },
        {
          "activity" : "generate2",
          "start" : 148,
          "length" : 136
        },
        {
          "activity" : "generateValidationPack",
          "start" : 174,
          "length" : 7
        }
      ]
    },
    {
      "name" : "fsh-generated/resources/StructureDefinition-fr-encounter-document.json",
      "size" : 4510,
      "processes" : [
        {
          "activity" : "loadResources",
          "start" : 53,
          "length" : 8
        },
        {
          "activity" : "load",
          "start" : 54,
          "length" : 11
        },
        {
          "activity" : "generateSnapshots",
          "start" : 57,
          "length" : 49
        },
        {
          "activity" : "generateNarratives",
          "start" : 59,
          "length" : 72
        },
        {
          "activity" : "validate",
          "start" : 77,
          "length" : 1102
        },
        {
          "activity" : "scanForUsageStats",
          "start" : 109,
          "length" : 1
        },
        {
          "activity" : "generate1",
          "start" : 114,
          "length" : 295
        },
        {
          "activity" : "generate2",
          "start" : 131,
          "length" : 600
        },
        {
          "activity" : "generate2",
          "start" : 148,
          "length" : 169
        },
        {
          "activity" : "generateValidationPack",
          "start" : 174,
          "length" : 16
        },
        {
          "activity" : "scanExamplesForR5",
          "start" : 207,
          "length" : 1
        }
      ]
    },
    {
      "name" : "fsh-generated/resources/StructureDefinition-fr-human-name-document.json",
      "size" : 1302,
      "processes" : [
        {
          "activity" : "loadResources",
          "start" : 53,
          "length" : 9
        },
        {
          "activity" : "load",
          "start" : 54,
          "length" : 9
        },
        {
          "activity" : "generateSnapshots",
          "start" : 57,
          "length" : 10
        },
        {
          "activity" : "generateNarratives",
          "start" : 59,
          "length" : 16
        },
        {
          "activity" : "validate",
          "start" : 78,
          "length" : 89
        },
        {
          "activity" : "checkConformanceResources",
          "start" : 109,
          "length" : 1
        },
        {
          "activity" : "generate1",
          "start" : 115,
          "length" : 46
        },
        {
          "activity" : "generate2",
          "start" : 131,
          "length" : 124
        },
        {
          "activity" : "generate2",
          "start" : 149,
          "length" : 104
        },
        {
          "activity" : "generateValidationPack",
          "start" : 174,
          "length" : 4
        },
        {
          "activity" : "scanExamplesForR5",
          "start" : 207,
          "length" : 1
        }
      ]
    },
    {
      "name" : "fsh-generated/resources/StructureDefinition-fr-location-document.json",
      "size" : 2027,
      "processes" : [
        {
          "activity" : "loadResources",
          "start" : 53,
          "length" : 9
        },
        {
          "activity" : "load",
          "start" : 54,
          "length" : 9
        },
        {
          "activity" : "generateSnapshots",
          "start" : 57,
          "length" : 27
        },
        {
          "activity" : "generateNarratives",
          "start" : 59,
          "length" : 34
        },
        {
          "activity" : "validate",
          "start" : 78,
          "length" : 586
        },
        {
          "activity" : "scanForUsageStats",
          "start" : 109,
          "length" : 1
        },
        {
          "activity" : "generate1",
          "start" : 115,
          "length" : 169
        },
        {
          "activity" : "generate2",
          "start" : 131,
          "length" : 257
        },
        {
          "activity" : "generate2",
          "start" : 149,
          "length" : 170
        },
        {
          "activity" : "generateValidationPack",
          "start" : 174,
          "length" : 6
        }
      ]
    },
    {
      "name" : "fsh-generated/resources/StructureDefinition-fr-organization-document.json",
      "size" : 1360,
      "processes" : [
        {
          "activity" : "loadResources",
          "start" : 53,
          "length" : 8
        },
        {
          "activity" : "load",
          "start" : 54,
          "length" : 10
        },
        {
          "activity" : "generateSnapshots",
          "start" : 57,
          "length" : 69
        },
        {
          "activity" : "generateNarratives",
          "start" : 59,
          "length" : 94
        },
        {
          "activity" : "validate",
          "start" : 78,
          "length" : 1781
        },
        {
          "activity" : "scanForUsageStats",
          "start" : 109,
          "length" : 2
        },
        {
          "activity" : "generate1",
          "start" : 115,
          "length" : 379
        },
        {
          "activity" : "generate2",
          "start" : 132,
          "length" : 877
        },
        {
          "activity" : "generate2",
          "start" : 149,
          "length" : 258
        },
        {
          "activity" : "generateValidationPack",
          "start" : 174,
          "length" : 14
        },
        {
          "activity" : "scanExamplesForR5",
          "start" : 207,
          "length" : 2
        }
      ]
    },
    {
      "name" : "fsh-generated/resources/StructureDefinition-fr-patient-document.json",
      "size" : 663,
      "processes" : [
        {
          "activity" : "loadResources",
          "start" : 53,
          "length" : 8
        },
        {
          "activity" : "load",
          "start" : 54,
          "length" : 8
        },
        {
          "activity" : "generateSnapshots",
          "start" : 57,
          "length" : 36
        },
        {
          "activity" : "generateNarratives",
          "start" : 59,
          "length" : 38
        },
        {
          "activity" : "validate",
          "start" : 80,
          "length" : 1117
        },
        {
          "activity" : "scanForUsageStats",
          "start" : 109,
          "length" : 2
        },
        {
          "activity" : "generate1",
          "start" : 115,
          "length" : 249
        },
        {
          "activity" : "generate2",
          "start" : 133,
          "length" : 757
        },
        {
          "activity" : "generate2",
          "start" : 149,
          "length" : 165
        },
        {
          "activity" : "generateValidationPack",
          "start" : 174,
          "length" : 9
        },
        {
          "activity" : "scanExamplesForR5",
          "start" : 207,
          "length" : 1
        }
      ]
    },
    {
      "name" : "fsh-generated/resources/StructureDefinition-fr-patient-ins-document.json",
      "size" : 4317,
      "processes" : [
        {
          "activity" : "loadResources",
          "start" : 53,
          "length" : 8
        },
        {
          "activity" : "load",
          "start" : 54,
          "length" : 10
        },
        {
          "activity" : "generateSnapshots",
          "start" : 57,
          "length" : 36
        },
        {
          "activity" : "generateNarratives",
          "start" : 59,
          "length" : 56
        },
        {
          "activity" : "validate",
          "start" : 81,
          "length" : 1359
        },
        {
          "activity" : "scanForUsageStats",
          "start" : 109,
          "length" : 1
        },
        {
          "activity" : "generate1",
          "start" : 116,
          "length" : 347
        },
        {
          "activity" : "generate2",
          "start" : 133,
          "length" : 837
        },
        {
          "activity" : "generate2",
          "start" : 149,
          "length" : 209
        },
        {
          "activity" : "generateValidationPack",
          "start" : 174,
          "length" : 16
        },
        {
          "activity" : "scanExamplesForR5",
          "start" : 207,
          "length" : 1
        }
      ]
    },
    {
      "name" : "fsh-generated/resources/StructureDefinition-fr-practitioner-document.json",
      "size" : 8780,
      "processes" : [
        {
          "activity" : "loadResources",
          "start" : 53,
          "length" : 9
        },
        {
          "activity" : "load",
          "start" : 54,
          "length" : 12
        },
        {
          "activity" : "generateSnapshots",
          "start" : 57,
          "length" : 47
        },
        {
          "activity" : "load-configure",
          "start" : 57,
          "length" : 1
        },
        {
          "activity" : "generateNarratives",
          "start" : 59,
          "length" : 68
        },
        {
          "activity" : "validate",
          "start" : 83,
          "length" : 2781
        },
        {
          "activity" : "checkConformanceResources",
          "start" : 109,
          "length" : 1
        },
        {
          "activity" : "scanForUsageStats",
          "start" : 109,
          "length" : 3
        },
        {
          "activity" : "generate1",
          "start" : 116,
          "length" : 590
        },
        {
          "activity" : "generate2",
          "start" : 134,
          "length" : 1509
        },
        {
          "activity" : "generate2",
          "start" : 149,
          "length" : 393
        },
        {
          "activity" : "generateValidationPack",
          "start" : 174,
          "length" : 20
        },
        {
          "activity" : "scanProfilesForR5",
          "start" : 207,
          "length" : 1
        },
        {
          "activity" : "scanExamplesForR5",
          "start" : 207,
          "length" : 2
        }
      ]
    },
    {
      "name" : "fsh-generated/resources/StructureDefinition-fr-practitionerRole-document.json",
      "size" : 3052,
      "processes" : [
        {
          "activity" : "loadResources",
          "start" : 53,
          "length" : 8
        },
        {
          "activity" : "load",
          "start" : 54,
          "length" : 10
        },
        {
          "activity" : "generateSnapshots",
          "start" : 57,
          "length" : 21
        },
        {
          "activity" : "generateNarratives",
          "start" : 59,
          "length" : 34
        },
        {
          "activity" : "validate",
          "start" : 85,
          "length" : 787
        },
        {
          "activity" : "scanForUsageStats",
          "start" : 109,
          "length" : 2
        },
        {
          "activity" : "generate1",
          "start" : 117,
          "length" : 224
        },
        {
          "activity" : "generate2",
          "start" : 136,
          "length" : 347
        },
        {
          "activity" : "generate2",
          "start" : 150,
          "length" : 141
        },
        {
          "activity" : "generateValidationPack",
          "start" : 174,
          "length" : 9
        },
        {
          "activity" : "scanExamplesForR5",
          "start" : 207,
          "length" : 1
        }
      ]
    },
    {
      "name" : "fsh-generated/resources/StructureDefinition-fr-related-person-document.json",
      "size" : 2061,
      "processes" : [
        {
          "activity" : "loadResources",
          "start" : 53,
          "length" : 8
        },
        {
          "activity" : "load",
          "start" : 54,
          "length" : 9
        },
        {
          "activity" : "generateSnapshots",
          "start" : 57,
          "length" : 17
        },
        {
          "activity" : "generateNarratives",
          "start" : 59,
          "length" : 22
        },
        {
          "activity" : "validate",
          "start" : 86,
          "length" : 496
        },
        {
          "activity" : "generate1",
          "start" : 117,
          "length" : 154
        },
        {
          "activity" : "generate2",
          "start" : 136,
          "length" : 213
        },
        {
          "activity" : "generate2",
          "start" : 150,
          "length" : 81
        },
        {
          "activity" : "generateValidationPack",
          "start" : 174,
          "length" : 6
        },
        {
          "activity" : "scanExamplesForR5",
          "start" : 207,
          "length" : 1
        }
      ]
    },
    {
      "name" : "fsh-generated/resources/ValueSet-fr-doc-vs-categorie-etablissement.json",
      "size" : 654,
      "processes" : [
        {
          "activity" : "loadResources",
          "start" : 53,
          "length" : 8
        },
        {
          "activity" : "load",
          "start" : 53,
          "length" : 12
        },
        {
          "activity" : "generateNarratives",
          "start" : 59,
          "length" : 78
        },
        {
          "activity" : "validate",
          "start" : 59,
          "length" : 1504
        },
        {
          "activity" : "generate1",
          "start" : 117,
          "length" : 18
        },
        {
          "activity" : "generate2",
          "start" : 136,
          "length" : 5153
        }
      ]
    },
    {
      "name" : "fsh-generated/resources/ValueSet-fr-doc-vs-participation-type.json",
      "size" : 790,
      "processes" : [
        {
          "activity" : "loadResources",
          "start" : 53,
          "length" : 7
        },
        {
          "activity" : "load",
          "start" : 53,
          "length" : 9
        },
        {
          "activity" : "generateNarratives",
          "start" : 59,
          "length" : 7
        },
        {
          "activity" : "validate",
          "start" : 61,
          "length" : 41
        },
        {
          "activity" : "generate1",
          "start" : 117,
          "length" : 18
        },
        {
          "activity" : "generate2",
          "start" : 141,
          "length" : 119
        }
      ]
    },
    {
      "name" : "fsh-generated/resources/ValueSet-fr-doc-vs-patient-contact-role.json",
      "size" : 887,
      "processes" : [
        {
          "activity" : "loadResources",
          "start" : 53,
          "length" : 8
        },
        {
          "activity" : "load",
          "start" : 53,
          "length" : 14
        },
        {
          "activity" : "checkR4R4B",
          "start" : 57,
          "length" : 1
        },
        {
          "activity" : "generateNarratives",
          "start" : 59,
          "length" : 7
        },
        {
          "activity" : "validate",
          "start" : 61,
          "length" : 54
        },
        {
          "activity" : "generate1",
          "start" : 117,
          "length" : 19
        },
        {
          "activity" : "generate2",
          "start" : 141,
          "length" : 106
        },
        {
          "activity" : "generateValidationPack",
          "start" : 174,
          "length" : 1
        }
      ]
    },
    {
      "name" : "fsh-generated/resources/ValueSet-fr-doc-vs-role-prise-charge.json",
      "size" : 683,
      "processes" : [
        {
          "activity" : "loadResources",
          "start" : 53,
          "length" : 8
        },
        {
          "activity" : "load",
          "start" : 53,
          "length" : 9
        },
        {
          "activity" : "generateNarratives",
          "start" : 59,
          "length" : 7
        },
        {
          "activity" : "validate",
          "start" : 61,
          "length" : 26
        },
        {
          "activity" : "generate1",
          "start" : 117,
          "length" : 17
        },
        {
          "activity" : "generate2",
          "start" : 142,
          "length" : 228
        }
      ]
    },
    {
      "name" : "fsh-generated/resources/ValueSet-fr-doc-vs-savoir-faire-profession-chirurgien-dentiste.json",
      "size" : 752,
      "processes" : [
        {
          "activity" : "loadResources",
          "start" : 53,
          "length" : 8
        },
        {
          "activity" : "load",
          "start" : 53,
          "length" : 9
        },
        {
          "activity" : "generateNarratives",
          "start" : 59,
          "length" : 11
        },
        {
          "activity" : "validate",
          "start" : 61,
          "length" : 23
        },
        {
          "activity" : "generate1",
          "start" : 117,
          "length" : 17
        },
        {
          "activity" : "generate2",
          "start" : 142,
          "length" : 281
        }
      ]
    },
    {
      "name" : "fsh-generated/resources/ValueSet-fr-doc-vs-savoir-faire-profession-infirmier.json",
      "size" : 703,
      "processes" : [
        {
          "activity" : "loadResources",
          "start" : 53,
          "length" : 8
        },
        {
          "activity" : "load",
          "start" : 53,
          "length" : 9
        },
        {
          "activity" : "generateNarratives",
          "start" : 59,
          "length" : 7
        },
        {
          "activity" : "validate",
          "start" : 61,
          "length" : 15
        },
        {
          "activity" : "generate1",
          "start" : 117,
          "length" : 19
        },
        {
          "activity" : "generate2",
          "start" : 142,
          "length" : 267
        }
      ]
    },
    {
      "name" : "fsh-generated/resources/ValueSet-fr-doc-vs-savoir-faire-profession-medecin.json",
      "size" : 1718,
      "processes" : [
        {
          "activity" : "loadResources",
          "start" : 53,
          "length" : 8
        },
        {
          "activity" : "load",
          "start" : 53,
          "length" : 9
        },
        {
          "activity" : "generateNarratives",
          "start" : 59,
          "length" : 15
        },
        {
          "activity" : "validate",
          "start" : 61,
          "length" : 67
        },
        {
          "activity" : "generate1",
          "start" : 117,
          "length" : 22
        },
        {
          "activity" : "generate2",
          "start" : 142,
          "length" : 530
        },
        {
          "activity" : "generateValidationPack",
          "start" : 174,
          "length" : 1
        }
      ]
    },
    {
      "name" : "fsh-generated/resources/ValueSet-fr-doc-vs-savoir-faire-profession-pharmacien.json",
      "size" : 841,
      "processes" : [
        {
          "activity" : "loadResources",
          "start" : 53,
          "length" : 7
        },
        {
          "activity" : "load",
          "start" : 53,
          "length" : 12
        },
        {
          "activity" : "load-configure",
          "start" : 57,
          "length" : 1
        },
        {
          "activity" : "generateNarratives",
          "start" : 59,
          "length" : 9
        },
        {
          "activity" : "validate",
          "start" : 61,
          "length" : 26
        },
        {
          "activity" : "generate1",
          "start" : 117,
          "length" : 17
        },
        {
          "activity" : "generate2",
          "start" : 143,
          "length" : 118
        }
      ]
    },
    {
      "name" : "fsh-generated/resources/ValueSet-fr-doc-vs-type-savoir-faire-profession-chirurgien-dentiste.json",
      "size" : 904,
      "processes" : [
        {
          "activity" : "loadResources",
          "start" : 53,
          "length" : 8
        },
        {
          "activity" : "load",
          "start" : 53,
          "length" : 17
        },
        {
          "activity" : "generateNarratives",
          "start" : 59,
          "length" : 8
        },
        {
          "activity" : "validate",
          "start" : 61,
          "length" : 19
        },
        {
          "activity" : "scanForUsageStats",
          "start" : 109,
          "length" : 1
        },
        {
          "activity" : "generate1",
          "start" : 117,
          "length" : 17
        },
        {
          "activity" : "generate2",
          "start" : 143,
          "length" : 95
        }
      ]
    },
    {
      "name" : "fsh-generated/resources/ValueSet-fr-doc-vs-type-savoir-faire-profession-infirmier.json",
      "size" : 854,
      "processes" : [
        {
          "activity" : "loadResources",
          "start" : 53,
          "length" : 8
        },
        {
          "activity" : "load",
          "start" : 53,
          "length" : 9
        },
        {
          "activity" : "generateNarratives",
          "start" : 59,
          "length" : 7
        },
        {
          "activity" : "validate",
          "start" : 61,
          "length" : 18
        },
        {
          "activity" : "generate1",
          "start" : 117,
          "length" : 18
        },
        {
          "activity" : "generate2",
          "start" : 143,
          "length" : 84
        },
        {
          "activity" : "generateValidationPack",
          "start" : 174,
          "length" : 1
        }
      ]
    },
    {
      "name" : "fsh-generated/resources/ValueSet-fr-doc-vs-type-savoir-faire-profession-medecin.json",
      "size" : 1813,
      "processes" : [
        {
          "activity" : "loadResources",
          "start" : 53,
          "length" : 8
        },
        {
          "activity" : "load",
          "start" : 53,
          "length" : 10
        },
        {
          "activity" : "checkR4R4B",
          "start" : 57,
          "length" : 1
        },
        {
          "activity" : "generateNarratives",
          "start" : 59,
          "length" : 7
        },
        {
          "activity" : "validate",
          "start" : 61,
          "length" : 20
        },
        {
          "activity" : "generate1",
          "start" : 117,
          "length" : 20
        },
        {
          "activity" : "generate2",
          "start" : 143,
          "length" : 95
        }
      ]
    },
    {
      "name" : "fsh-generated/resources/ValueSet-fr-doc-vs-type-savoir-faire-profession-pharmacien.json",
      "size" : 972,
      "processes" : [
        {
          "activity" : "loadResources",
          "start" : 53,
          "length" : 8
        },
        {
          "activity" : "load",
          "start" : 53,
          "length" : 9
        },
        {
          "activity" : "generateNarratives",
          "start" : 59,
          "length" : 7
        },
        {
          "activity" : "validate",
          "start" : 61,
          "length" : 17
        },
        {
          "activity" : "generate1",
          "start" : 117,
          "length" : 18
        },
        {
          "activity" : "generate2",
          "start" : 143,
          "length" : 118
        }
      ]
    }
  ]
}
